christmas_card/__init__.py
christmas_card/__main__.py
christmas_card/cli.py
christmas_card/encrypt.py
christmas_card/encrypted_card.md
christmas_card/images/fireplace.png
christmas_card/images/santa.png
christmas_card-2023.0.0.dist-info/METADATA
christmas_card-2023.0.0.dist-info/WHEEL
christmas_card-2023.0.0.dist-info/entry_points.txt
christmas_card-2023.0.0.dist-info/RECORD
