Metadata-Version: 2.1
Name: christmas-card
Version: 2023.0.0
Summary: A christmas card
License: MIT
Author: Your Name
Author-email: you@example.com
Requires-Python: >=3.9,<4.0
Classifier: License :: OSI Approved :: MIT License
Classifier: Programming Language :: Python :: 3
Classifier: Programming Language :: Python :: 3.9
Classifier: Programming Language :: Python :: 3.10
Classifier: Programming Language :: Python :: 3.11
Classifier: Programming Language :: Python :: 3.12
Requires-Dist: cryptography (>=41.0.7,<42.0.0)
Requires-Dist: rich (>=13.7.0,<14.0.0)
Requires-Dist: rich-pixels[image] (>=2.1.1,<3.0.0)
Requires-Dist: textual (>=0.45.1,<0.46.0)
Requires-Dist: typer (>=0.9.0,<0.10.0)
